xhac/__init__.py
xhac/cli.py
xhac/client.py
xhac/model.py
xhac/pyparser.py
xhac/scanner.py
xhac/shell.py
xhac/util.py
xhac-0.1.31.dist-info/METADATA
xhac-0.1.31.dist-info/WHEEL
xhac-0.1.31.dist-info/entry_points.txt
xhac-0.1.31.dist-info/licenses/LICENSE
xhac-0.1.31.dist-info/RECORD
