Metadata-Version: 2.3
Name: xhac
Version: 0.1.31
Summary: MXCHIP Home Access Client
Project-URL: Homepage, https://www.mxchip.com/
Project-URL: Documentation, https://www.mxchip.com/
Project-URL: Repository, https://www.mxchip.com/
Project-URL: Changelog, https://www.mxchip.com/
Author-email: Snow Yang <yangsw@mxchip.com>
Maintainer-email: Snow Yang <yangsw@mxchip.com>
License: Copyright (c) 2018 The Python Packaging Authority
License-File: LICENSE
Keywords: MXCHIP,mxchip
Classifier: Development Status :: 4 - Beta
Classifier: License :: OSI Approved :: MIT License
Classifier: Programming Language :: Python :: 3
Requires-Python: >=3.10
Requires-Dist: async-timeout<=4.0.2
Requires-Dist: chacha20poly1305
Requires-Dist: click
Requires-Dist: cmd2
Requires-Dist: hkdf
Requires-Dist: rich
Requires-Dist: srp
Requires-Dist: zeroconf
